Workbook

Sheet Dashboard Resumen
B2: DASHBOARD DE RECURSOS HUMANOS
B4: Total Empleados | E4: Nómina Mensual Total | H4: Salario Promedio
B5: =COUNTA('Base de Datos Empleados'!A2:A301) | E5: =SUM('Base de Datos Empleados'!G2:G301) | H5: =AVERAGE('Base de Datos Empleados'!G2:G301)
B8: Resumen por Departamento
B9: Departamento | C9: Nº Empleados | D9: Nómina Total | E9: Salario Promedio
B10: Ventas | C10: =COUNTIF('Base de Datos Empleados'!$C$2:$C$301, B10) | D10: =SUMIF('Base de Datos Empleados'!$C$2:$C$301, B10, 'Base de Datos Empleados'!$G$2:$G$301) | E10: =AVERAGEIF('Base de Datos Empleados'!$C$2:$C$301, B10, 'Base de Datos Empleados'!$G$2:$G$301)
B11: Compras | C11: =COUNTIF('Base de Datos Empleados'!$C$2:$C$301, B11) | D11: =SUMIF('Base de Datos Empleados'!$C$2:$C$301, B11, 'Base de Datos Empleados'!$G$2:$G$301) | E11: =AVERAGEIF('Base de Datos Empleados'!$C$2:$C$301, B11, 'Base de Datos Empleados'!$G$2:$G$301)
B12: Sistemas | C12: =COUNTIF('Base de Datos Empleados'!$C$2:$C$301, B12) | D12: =SUMIF('Base de Datos Empleados'!$C$2:$C$301, B12, 'Base de Datos Empleados'!$G$2:$G$301) | E12: =AVERAGEIF('Base de Datos Empleados'!$C$2:$C$301, B12, 'Base de Datos Empleados'!$G$2:$G$301)
B13: Recursos Humanos | C13: =COUNTIF('Base de Datos Empleados'!$C$2:$C$301, B13) | D13: =SUMIF('Base de Datos Empleados'!$C$2:$C$301, B13, 'Base de Datos Empleados'!$G$2:$G$301) | E13: =AVERAGEIF('Base de Datos Empleados'!$C$2:$C$301, B13, 'Base de Datos Empleados'!$G$2:$G$301)
B14: Contabilidad | C14: =COUNTIF('Base de Datos Empleados'!$C$2:$C$301, B14) | D14: =SUMIF('Base de Datos Empleados'!$C$2:$C$301, B14, 'Base de Datos Empleados'!$G$2:$G$301) | E14: =AVERAGEIF('Base de Datos Empleados'!$C$2:$C$301, B14, 'Base de Datos Empleados'!$G$2:$G$301)
B15: Marketing | C15: =COUNTIF('Base de Datos Empleados'!$C$2:$C$301, B15) | D15: =SUMIF('Base de Datos Empleados'!$C$2:$C$301, B15, 'Base de Datos Empleados'!$G$2:$G$301) | E15: =AVERAGEIF('Base de Datos Empleados'!$C$2:$C$301, B15, 'Base de Datos Empleados'!$G$2:$G$301)
B16: Operaciones | C16: =COUNTIF('Base de Datos Empleados'!$C$2:$C$301, B16) | D16: =SUMIF('Base de Datos Empleados'!$C$2:$C$301, B16, 'Base de Datos Empleados'!$G$2:$G$301) | E16: =AVERAGEIF('Base de Datos Empleados'!$C$2:$C$301, B16, 'Base de Datos Empleados'!$G$2:$G$301)
B17: Total General | C17: =SUM(C10:C16) | D17: =SUM(D10:D16) | E17: =AVERAGE('Base de Datos Empleados'!G2:G301)

Sheet Base de Datos Empleados
A1: No. Empleado | B1: Nombre | C1: Departamento | D1: Jefe | E1: Teléfono | F1: Puesto | G1: Salario | H1: Fecha de Ingreso | I1: Correo Electrónico | J1: Estatus
A2: 101 | B2: Juan Pérez | C2: Ventas | D2: Laura Gómez | E2: 555-1234 | F2: Ejecutivo | G2: 14500 | H2: 44972 | I2: juan.perez@empresa.com | J2: Activo
A3: 102 | B3: Ana Ruiz | C3: Compras | D3: Carlos Díaz | E3: 555-2345 | F3: Auxiliar | G3: 11800 | H3: 45301 | I3: ana.ruiz@empresa.com | J3: Activo
A4: 103 | B4: Luis Torres | C4: Sistemas | D4: Miguel López | E4: 555-3456 | F4: Programador | G4: 18500 | H4: 44812 | I4: luis.torres@empresa.com | J4: Activo
A5: 104 | B5: Ricardo Gómez Pérez | C5: Marketing | D5: Sofía Castro | E5: 555-4657 | F5: Coordinador de Marketing | G5: 20200 | H5: 43672 | I5: ricardo.gomez104@empresa.com | J5: Activo
A6: 105 | B6: Andrea Mendoza Castro | C6: Contabilidad | D6: Roberto Méndez | E6: 555-7912 | F6: Auxiliar Contable | G6: 17800 | H6: 43231 | I6: andrea.mendoza@empresa.com | J6: Activo
A7: 106 | B7: Pedro Rodríguez García | C7: Contabilidad | D7: Roberto Méndez | E7: 555-4257 | F7: Auxiliar Contable | G7: 17500 | H7: 46033 | I7: pedro.rodriguez@empresa.com | J7: Activo
A8: 107 | B8: Sofía Castillo Reyes | C8: Sistemas | D8: Miguel López | E8: 555-7924 | F8: Programador | G8: 24700 | H8: 44494 | I8: sofia.castillo@empresa.com | J8: Activo
A9: 108 | B9: Pedro Ramos Sánchez | C9: Ventas | D9: Laura Gómez | E9: 555-2584 | F9: Ejecutivo de Ventas | G9: 21800 | H9: 44571 | I9: pedro.ramos108@empresa.com | J9: Activo
A10: 109 | B10: Gabriela Martínez Chávez | C10: Ventas | D10: Laura Gómez | E10: 555-3045 | F10: Gerente de Ventas | G10: 34700 | H10: 44651 | I10: gabriela.martinez@empresa.com | J10: Activo
A11: 110 | B11: Elena Rivera Álvarez | C11: Contabilidad | D11: Roberto Méndez | E11: 555-4150 | F11: Auditor Interno | G11: 35800 | H11: 45986 | I11: elena.rivera@empresa.com | J11: Activo
A12: 111 | B12: Andrea Rodríguez Ramos | C12: Sistemas | D12: Miguel López | E12: 555-2654 | F12: Programador | G12: 27100 | H12: 44657 | I12: andrea.rodriguez@empresa.com | J12: Activo
A13: 112 | B13: Ricardo Rivera Ramírez | C13: Compras | D13: Carlos Díaz | E13: 555-4432 | F13: Especialista de Abastecimiento | G13: 20100 | H13: 45846 | I13: ricardo.rivera@empresa.com | J13: Activo
... A301: 400 | B301: Juan Mendoza González | C301: Contabilidad | D301: Roberto Méndez | E301: 555-7941 | F301: Auxiliar Contable | G301: 13300 | H301: 44512 | I301: juan.mendoza400@empresa.com | J301: Activo
